{
  "version": "2026-07-18",
  "updated": "2026-07-18",
  "entries": [
    {
      "claimId": "13flow:claim-53b32247e6add3",
      "reviewedAt": "2026-06-28T08:04:31.122Z",
      "reviewedBy": "bluetouff",
      "kind": "inférence",
      "note": "check ok"
    },
    {
      "claimId": "13flow:claim-cfe7bde8c56261",
      "reviewedAt": "2026-06-28T08:04:50.042Z",
      "reviewedBy": "bluetouff",
      "kind": "unclassified-assertion",
      "note": "check ok"
    },
    {
      "claimId": "accord-paix-ormuz-rouvre-scenarios:claim-0189c9bb8eabac",
      "reviewedAt": "2026-06-28T08:03:55.419Z",
      "reviewedBy": "bluetouff",
      "kind": "unclassified-assertion",
      "note": "check ok"
    },
    {
      "claimId": "accord-paix-ormuz-rouvre-scenarios:claim-703c85d3fa2634",
      "reviewedAt": "2026-06-28T08:03:37.840Z",
      "reviewedBy": "bluetouff",
      "kind": "unclassified-assertion",
      "note": "check ok"
    },
    {
      "claimId": "accord-paix-ormuz-rouvre-scenarios:claim-a364242f456334",
      "reviewedAt": "2026-06-28T08:02:41.284Z",
      "reviewedBy": "bluetouff",
      "kind": "unclassified-assertion",
      "note": "check ok"
    },
    {
      "claimId": "accord-paix-ormuz-rouvre-scenarios:claim-a498b1a9981685",
      "reviewedAt": "2026-06-28T08:02:59.112Z",
      "reviewedBy": "bluetouff",
      "kind": "unclassified-assertion",
      "note": "check ok"
    },
    {
      "claimId": "accord-paix-ormuz-rouvre-scenarios:claim-d2e323cff72337",
      "reviewedAt": "2026-06-28T08:03:18.566Z",
      "reviewedBy": "bluetouff",
      "kind": "unclassified-assertion",
      "note": "check ok"
    },
    {
      "claimId": "basis-trade-treasuries-levier:claim-285095ef708d55",
      "reviewedAt": "2026-06-28T07:29:08.355Z",
      "reviewedBy": "bluetouff",
      "kind": "unclassified-assertion",
      "note": "check ok"
    },
    {
      "claimId": "basis-trade-treasuries-levier:claim-6a2d036e95420f",
      "reviewedAt": "2026-06-28T07:28:26.774Z",
      "reviewedBy": "bluetouff",
      "kind": "unclassified-assertion",
      "note": "check ok"
    },
    {
      "claimId": "basis-trade-treasuries-levier:claim-b2a2577711a31a",
      "reviewedAt": "2026-06-28T07:28:49.869Z",
      "reviewedBy": "bluetouff",
      "kind": "unclassified-assertion",
      "note": "check ok"
    },
    {
      "claimId": "binance-mica-lagarde:claim-4b48c47bced437",
      "reviewedAt": "2026-06-28T07:49:08.314Z",
      "reviewedBy": "bluetouff",
      "kind": "unclassified-assertion",
      "note": "check ok"
    },
    {
      "claimId": "binance-mica-lagarde:claim-af759f2c8b3a3b",
      "reviewedAt": "2026-06-28T07:48:44.743Z",
      "reviewedBy": "bluetouff",
      "kind": "unclassified-assertion",
      "note": "check ok"
    },
    {
      "claimId": "binance-mica-lagarde:claim-f1e70ec911a948",
      "reviewedAt": "2026-06-28T07:48:24.640Z",
      "reviewedBy": "bluetouff",
      "kind": "unclassified-assertion",
      "note": "check ok"
    },
    {
      "claimId": "boom-ia-bis-fragilite-financiere:claim-e3603be4179fd4",
      "reviewedAt": "2026-06-29T18:14:42.706Z",
      "reviewedBy": "bluetouff",
      "kind": "unclassified-assertion",
      "note": "Chiffres vérifiés"
    },
    {
      "claimId": "boom-ia-bis-fragilite-financiere:claim-fde669da43bb9e",
      "reviewedAt": "2026-06-29T18:16:16.912Z",
      "reviewedBy": "bluetouff",
      "kind": "scénario",
      "note": "Hypothèse pertinente, à confirmer dans le temps."
    },
    {
      "claimId": "chine-importations-petrole-brut-chute-2026:claim-617f0c5b6887c7",
      "reviewedAt": "2026-06-28T07:25:55.868Z",
      "reviewedBy": "bluetouff",
      "kind": "unclassified-assertion",
      "note": "check ok"
    },
    {
      "claimId": "chine-importations-petrole-brut-chute-2026:claim-dba0e036364aa8",
      "reviewedAt": "2026-06-28T07:25:32.268Z",
      "reviewedBy": "bluetouff",
      "kind": "inférence",
      "note": "check ok"
    },
    {
      "claimId": "clarity-act-trump-obstacle-conflit-interets:claim-68016c47d7af12",
      "reviewedAt": "2026-06-28T07:33:44.807Z",
      "reviewedBy": "bluetouff",
      "kind": "unclassified-assertion",
      "note": "check ok"
    },
    {
      "claimId": "clarity-act-trump-obstacle-conflit-interets:claim-157cef25e16289",
      "reviewedAt": "2026-07-07T16:40:00.000Z",
      "reviewedBy": "Codex",
      "kind": "unclassified-assertion",
      "note": "Mise a jour 7/7/2026 verifiee contre la publication OGE du 30 juin 2026."
    },
    {
      "claimId": "clarity-act-trump-obstacle-conflit-interets:claim-0514d487421a35",
      "reviewedAt": "2026-07-07T16:41:00.000Z",
      "reviewedBy": "Codex",
      "kind": "unclassified-assertion",
      "note": "Montants et mentions OGE recoupes avec le rapport 278e, MarketWatch, The New Yorker et WSJ."
    },
    {
      "claimId": "clarity-act-trump-obstacle-conflit-interets:claim-903a0485e399bd",
      "reviewedAt": "2026-07-07T16:42:00.000Z",
      "reviewedBy": "Codex",
      "kind": "estimation",
      "note": "Position de la Maison Blanche attribuee a Anna Kelly via Business Insider."
    },
    {
      "claimId": "clarity-act-trump-obstacle-conflit-interets:claim-80cced4868b186",
      "reviewedAt": "2026-06-28T07:34:12.522Z",
      "reviewedBy": "bluetouff",
      "kind": "estimation",
      "note": "check ok"
    },
    {
      "claimId": "clarity-act-trump-obstacle-conflit-interets:claim-b576b4052c0d5f",
      "reviewedAt": "2026-06-28T07:33:25.482Z",
      "reviewedBy": "bluetouff",
      "kind": "unclassified-assertion",
      "note": "check ok"
    },
    {
      "claimId": "collateral-rehypothecation-cle-de-voute:claim-b046e5dcaa6614",
      "reviewedAt": "2026-06-28T07:20:25.279Z",
      "reviewedBy": "bluetouff",
      "kind": "unclassified-assertion",
      "note": "check ok"
    },
    {
      "claimId": "credit-prive-juin-2026-defaut-record-gating:claim-0c78f5d722dc22",
      "reviewedAt": "2026-06-28T08:01:40.882Z",
      "reviewedBy": "bluetouff",
      "kind": "unclassified-assertion",
      "note": "check ok"
    },
    {
      "claimId": "credit-prive-juin-2026-defaut-record-gating:claim-1c8e48ab954e61",
      "reviewedAt": "2026-06-28T08:00:45.831Z",
      "reviewedBy": "bluetouff",
      "kind": "estimation",
      "note": "check ok"
    },
    {
      "claimId": "credit-prive-juin-2026-defaut-record-gating:claim-2c9beac9ab88b0",
      "reviewedAt": "2026-06-28T07:59:17.445Z",
      "reviewedBy": "bluetouff",
      "kind": "estimation",
      "note": "check ok"
    },
    {
      "claimId": "credit-prive-juin-2026-defaut-record-gating:claim-2fc65da2d24178",
      "reviewedAt": "2026-06-28T07:59:34.612Z",
      "reviewedBy": "bluetouff",
      "kind": "unclassified-assertion",
      "note": "check ok"
    },
    {
      "claimId": "credit-prive-juin-2026-defaut-record-gating:claim-33e6a2abc623e3",
      "reviewedAt": "2026-06-28T08:02:00.868Z",
      "reviewedBy": "bluetouff",
      "kind": "unclassified-assertion",
      "note": "check ok"
    },
    {
      "claimId": "credit-prive-juin-2026-defaut-record-gating:claim-4de35738b7cae1",
      "reviewedAt": "2026-06-28T08:01:02.486Z",
      "reviewedBy": "bluetouff",
      "kind": "unclassified-assertion",
      "note": "check ok"
    },
    {
      "claimId": "credit-prive-juin-2026-defaut-record-gating:claim-534dd74dba7273",
      "reviewedAt": "2026-06-28T07:54:24.293Z",
      "reviewedBy": "bluetouff",
      "kind": "estimation",
      "note": "check ok"
    },
    {
      "claimId": "credit-prive-juin-2026-defaut-record-gating:claim-6c57db821d8979",
      "reviewedAt": "2026-06-28T07:53:43.025Z",
      "reviewedBy": "bluetouff",
      "kind": "unclassified-assertion",
      "note": "check ok"
    },
    {
      "claimId": "credit-prive-juin-2026-defaut-record-gating:claim-7386b97a44ea7c",
      "reviewedAt": "2026-06-28T08:02:22.615Z",
      "reviewedBy": "bluetouff",
      "kind": "unclassified-assertion",
      "note": "check ok"
    },
    {
      "claimId": "credit-prive-juin-2026-defaut-record-gating:claim-9a707c30348d08",
      "reviewedAt": "2026-06-28T08:00:11.375Z",
      "reviewedBy": "bluetouff",
      "kind": "unclassified-assertion",
      "note": "check ok"
    },
    {
      "claimId": "credit-prive-juin-2026-defaut-record-gating:claim-a5a15f665e4d80",
      "reviewedAt": "2026-06-28T08:00:28.880Z",
      "reviewedBy": "bluetouff",
      "kind": "scénario",
      "note": "check ok"
    },
    {
      "claimId": "credit-prive-juin-2026-defaut-record-gating:claim-a9b6545f3dc87f",
      "reviewedAt": "2026-06-28T08:01:21.445Z",
      "reviewedBy": "bluetouff",
      "kind": "unclassified-assertion",
      "note": "check ok"
    },
    {
      "claimId": "credit-prive-juin-2026-defaut-record-gating:claim-d556cbace8b1aa",
      "reviewedAt": "2026-06-28T07:59:53.293Z",
      "reviewedBy": "bluetouff",
      "kind": "unclassified-assertion",
      "note": "check ok"
    },
    {
      "claimId": "credit-prive-rachats-mega-ipo:claim-6cb649e90bb86d",
      "reviewedAt": "2026-06-28T07:45:36.541Z",
      "reviewedBy": "bluetouff",
      "kind": "estimation",
      "note": "check ok"
    },
    {
      "claimId": "credit-prive-rachats-mega-ipo:claim-8b9ae954df5116",
      "reviewedAt": "2026-06-28T07:47:53.459Z",
      "reviewedBy": "bluetouff",
      "kind": "unclassified-assertion",
      "note": "check ok"
    },
    {
      "claimId": "credit-prive-rachats-mega-ipo:claim-aff1606323dba9",
      "reviewedAt": "2026-06-28T07:46:16.981Z",
      "reviewedBy": "bluetouff",
      "kind": "unclassified-assertion",
      "note": "check ok"
    },
    {
      "claimId": "credit-prive-rachats-mega-ipo:claim-b4dad33629a623",
      "reviewedAt": "2026-06-28T07:46:36.976Z",
      "reviewedBy": "bluetouff",
      "kind": "unclassified-assertion",
      "note": "check ok"
    },
    {
      "claimId": "credit-prive-rachats-mega-ipo:claim-faf6eb86d2de76",
      "reviewedAt": "2026-06-28T07:45:58.028Z",
      "reviewedBy": "bluetouff",
      "kind": "unclassified-assertion",
      "note": "check ok"
    },
    {
      "claimId": "crise-ormuz-asie-impacts-economiques:claim-019f2ca689f20f",
      "reviewedAt": "2026-06-28T07:39:13.625Z",
      "reviewedBy": "bluetouff",
      "kind": "estimation",
      "note": "check ok"
    },
    {
      "claimId": "crise-ormuz-asie-impacts-economiques:claim-0792b4531da7bb",
      "reviewedAt": "2026-06-28T07:35:32.557Z",
      "reviewedBy": "bluetouff",
      "kind": "scénario",
      "note": "check ok"
    },
    {
      "claimId": "crise-ormuz-asie-impacts-economiques:claim-6e4893b9c53747",
      "reviewedAt": "2026-06-28T07:36:45.766Z",
      "reviewedBy": "bluetouff",
      "kind": "unclassified-assertion",
      "note": "check ok"
    },
    {
      "claimId": "crise-ormuz-asie-impacts-economiques:claim-7c243fe0228deb",
      "reviewedAt": "2026-06-28T07:35:54.301Z",
      "reviewedBy": "bluetouff",
      "kind": "scénario",
      "note": "check ok"
    },
    {
      "claimId": "crise-ormuz-asie-impacts-economiques:claim-a3fba3b4c379a7",
      "reviewedAt": "2026-06-28T07:37:52.168Z",
      "reviewedBy": "bluetouff",
      "kind": "unclassified-assertion",
      "note": "check ok"
    },
    {
      "claimId": "crise-ormuz-asie-impacts-economiques:claim-b058149b66fef6",
      "reviewedAt": "2026-06-28T07:34:50.552Z",
      "reviewedBy": "bluetouff",
      "kind": "inférence",
      "note": "check ok"
    },
    {
      "claimId": "crise-ormuz-asie-impacts-economiques:claim-ba4e8e92ff9d58",
      "reviewedAt": "2026-06-28T07:37:06.236Z",
      "reviewedBy": "bluetouff",
      "kind": "estimation",
      "note": "check ok"
    },
    {
      "claimId": "crise-ormuz-asie-impacts-economiques:claim-efc59f9372767d",
      "reviewedAt": "2026-06-28T07:36:19.734Z",
      "reviewedBy": "bluetouff",
      "kind": "scénario",
      "note": "check ok"
    },
    {
      "claimId": "crise-ormuz-asie-impacts-economiques:claim-f2f696230472fd",
      "reviewedAt": "2026-06-28T07:39:33.455Z",
      "reviewedBy": "bluetouff",
      "kind": "scénario",
      "note": "check ok"
    },
    {
      "claimId": "cross-currency-basis-prix-cache-dollar:claim-3f8649e162f528",
      "reviewedAt": "2026-06-28T07:26:20.997Z",
      "reviewedBy": "bluetouff",
      "kind": "unclassified-assertion",
      "note": "check ok"
    },
    {
      "claimId": "cuivre-shortage-ormuz-el-nino-2026:claim-24a4dba17ef846",
      "reviewedAt": "2026-06-28T07:20:48.785Z",
      "reviewedBy": "bluetouff",
      "kind": "unclassified-assertion",
      "note": "check ok"
    },
    {
      "claimId": "cuivre-shortage-ormuz-el-nino-2026:claim-32a9d6b5aaa8f5",
      "reviewedAt": "2026-06-28T07:24:41.821Z",
      "reviewedBy": "bluetouff",
      "kind": "scénario",
      "note": "check ok"
    },
    {
      "claimId": "cuivre-shortage-ormuz-el-nino-2026:claim-407ea295053139",
      "reviewedAt": "2026-06-28T07:22:20.535Z",
      "reviewedBy": "bluetouff",
      "kind": "unclassified-assertion",
      "note": "check ok"
    },
    {
      "claimId": "cuivre-shortage-ormuz-el-nino-2026:claim-45c8a3da860316",
      "reviewedAt": "2026-06-28T07:21:37.828Z",
      "reviewedBy": "bluetouff",
      "kind": "estimation",
      "note": "check ok"
    },
    {
      "claimId": "cuivre-shortage-ormuz-el-nino-2026:claim-4b2765994e2dab",
      "reviewedAt": "2026-06-28T07:21:07.094Z",
      "reviewedBy": "bluetouff",
      "kind": "unclassified-assertion",
      "note": "check ok"
    },
    {
      "claimId": "cuivre-shortage-ormuz-el-nino-2026:claim-b2947cac98307f",
      "reviewedAt": "2026-06-28T07:25:07.033Z",
      "reviewedBy": "bluetouff",
      "kind": "unclassified-assertion",
      "note": "check ok"
    },
    {
      "claimId": "cuivre-shortage-ormuz-el-nino-2026:claim-b74f29ebd1f3ed",
      "reviewedAt": "2026-06-28T07:22:58.243Z",
      "reviewedBy": "bluetouff",
      "kind": "estimation",
      "note": "check ok"
    },
    {
      "claimId": "cuivre-shortage-ormuz-el-nino-2026:claim-d2da42dfafa444",
      "reviewedAt": "2026-06-28T07:23:36.535Z",
      "reviewedBy": "bluetouff",
      "kind": "unclassified-assertion",
      "note": "check ok"
    },
    {
      "claimId": "cuivre-shortage-ormuz-el-nino-2026:claim-d5fb8ecc4bfb4a",
      "reviewedAt": "2026-06-28T07:22:02.127Z",
      "reviewedBy": "bluetouff",
      "kind": "unclassified-assertion",
      "note": "check ok"
    },
    {
      "claimId": "cuivre-shortage-ormuz-el-nino-2026:claim-e32f905b71ef6e",
      "reviewedAt": "2026-06-28T07:23:56.250Z",
      "reviewedBy": "bluetouff",
      "kind": "unclassified-assertion",
      "note": "check ok"
    },
    {
      "claimId": "dedollarisation-recit-vs-chiffres:claim-f2e19f1bb4cebd",
      "reviewedAt": "2026-06-28T07:34:31.069Z",
      "reviewedBy": "bluetouff",
      "kind": "unclassified-assertion",
      "note": "check ok"
    },
    {
      "claimId": "dollar-yen-intervention-risque-carry-2026:claim-5fd613b6105a3b",
      "reviewedAt": "2026-06-28T07:19:16.594Z",
      "reviewedBy": "bluetouff",
      "kind": "unclassified-assertion",
      "note": "check ok"
    },
    {
      "claimId": "dollar-yen-intervention-risque-carry-2026:claim-a622081519e44a",
      "reviewedAt": "2026-06-28T07:20:07.050Z",
      "reviewedBy": "bluetouff",
      "kind": "unclassified-assertion",
      "note": "check ok"
    },
    {
      "claimId": "dollar-yen-intervention-risque-carry-2026:claim-d83e454169d426",
      "reviewedAt": "2026-06-28T07:19:40.293Z",
      "reviewedBy": "bluetouff",
      "kind": "unclassified-assertion",
      "note": "check ok"
    },
    {
      "claimId": "economie-des-intentions:claim-28a84c8169e916",
      "reviewedAt": "2026-06-28T07:41:14.870Z",
      "reviewedBy": "bluetouff",
      "kind": "unclassified-assertion",
      "note": "check ok"
    },
    {
      "claimId": "economie-des-intentions:claim-4f53dee44bc3b2",
      "reviewedAt": "2026-06-28T07:39:54.753Z",
      "reviewedBy": "bluetouff",
      "kind": "unclassified-assertion",
      "note": "check ok"
    },
    {
      "claimId": "economie-des-intentions:claim-56eba8661d5495",
      "reviewedAt": "2026-06-28T07:41:44.556Z",
      "reviewedBy": "bluetouff",
      "kind": "unclassified-assertion",
      "note": "check ok"
    },
    {
      "claimId": "economie-des-intentions:claim-5afd2c60148f00",
      "reviewedAt": "2026-06-28T07:40:34.779Z",
      "reviewedBy": "bluetouff",
      "kind": "unclassified-assertion",
      "note": "check ok"
    },
    {
      "claimId": "economie-des-intentions:claim-85e673cedcdeb3",
      "reviewedAt": "2026-06-28T07:42:29.567Z",
      "reviewedBy": "bluetouff",
      "kind": "unclassified-assertion",
      "note": "check ok"
    },
    {
      "claimId": "economie-des-intentions:claim-8aedf226d8a7cb",
      "reviewedAt": "2026-06-28T07:40:56.267Z",
      "reviewedBy": "bluetouff",
      "kind": "estimation",
      "note": "check ok"
    },
    {
      "claimId": "economie-des-intentions:claim-9a8aaa18958ae7",
      "reviewedAt": "2026-06-28T07:45:17.509Z",
      "reviewedBy": "bluetouff",
      "kind": "unclassified-assertion",
      "note": "check ok"
    },
    {
      "claimId": "economie-des-intentions:claim-c28e7eb19fbbfb",
      "reviewedAt": "2026-06-28T07:40:15.537Z",
      "reviewedBy": "bluetouff",
      "kind": "unclassified-assertion",
      "note": "check ok"
    },
    {
      "claimId": "economie-des-intentions:claim-e922b0810a7cb9",
      "reviewedAt": "2026-06-28T07:42:52.357Z",
      "reviewedBy": "bluetouff",
      "kind": "unclassified-assertion",
      "note": "check ok"
    },
    {
      "claimId": "economie-des-intentions:claim-f637b140c0efae",
      "reviewedAt": "2026-06-28T07:42:10.196Z",
      "reviewedBy": "bluetouff",
      "kind": "unclassified-assertion",
      "note": "check ok"
    },
    {
      "claimId": "eurodollars-dollar-offshore-dette-cachee:claim-5f34013c718f08",
      "reviewedAt": "2026-06-28T07:26:44.092Z",
      "reviewedBy": "bluetouff",
      "kind": "unclassified-assertion",
      "note": "check ok"
    },
    {
      "claimId": "financement-circulaire-ia:claim-56c9571b29c460",
      "reviewedAt": "2026-06-28T07:18:54.453Z",
      "reviewedBy": "bluetouff",
      "kind": "unclassified-assertion",
      "note": "check ok"
    },
    {
      "claimId": "hyperliquid-bourse-onchain-tradfi:claim-78b6f547223a7b",
      "reviewedAt": "2026-06-28T17:43:30.636Z",
      "reviewedBy": "bluetouff",
      "kind": "unclassified-assertion",
      "note": "Perfs carnet d’ordres on-chain, dilution, buyback et offre en circulation confirmés"
    },
    {
      "claimId": "inflation-us-grand-come-back:claim-31c0d448005c81",
      "reviewedAt": "2026-06-28T08:08:31.628Z",
      "reviewedBy": "bluetouff",
      "kind": "unclassified-assertion",
      "note": "check ok"
    },
    {
      "claimId": "iran-peages-ormuz-usdt-tron-ofac:claim-885d90c6d932f4",
      "reviewedAt": "2026-06-28T08:09:30.112Z",
      "reviewedBy": "bluetouff",
      "kind": "unclassified-assertion",
      "note": "check ok"
    },
    {
      "claimId": "iran-peages-ormuz-usdt-tron-ofac:claim-bb3d69478293e7",
      "reviewedAt": "2026-06-28T08:10:16.362Z",
      "reviewedBy": "bluetouff",
      "kind": "unclassified-assertion",
      "note": "check ok"
    },
    {
      "claimId": "iran-peages-ormuz-usdt-tron-ofac:claim-c1a4d52c5b4771",
      "reviewedAt": "2026-06-28T08:09:50.288Z",
      "reviewedBy": "bluetouff",
      "kind": "estimation",
      "note": "check ok"
    },
    {
      "claimId": "la-contagion-silencieuse-credit-prive:claim-e091e3ae0424ed",
      "reviewedAt": "2026-06-28T08:07:15.791Z",
      "reviewedBy": "bluetouff",
      "kind": "unclassified-assertion",
      "note": "check ok"
    },
    {
      "claimId": "la-guerre-diran-2026-seisme-economique-politique:claim-16d03fc1686227",
      "reviewedAt": "2026-06-28T08:07:54.501Z",
      "reviewedBy": "bluetouff",
      "kind": "scénario",
      "note": "check ok"
    },
    {
      "claimId": "le-peuple-americain-actionnaire-de-lia-decryptage-dun-scam-presidentiel:claim-a8aef95fdfc456",
      "reviewedAt": "2026-06-28T08:06:56.630Z",
      "reviewedBy": "bluetouff",
      "kind": "unclassified-assertion",
      "note": "check ok"
    },
    {
      "claimId": "liban-perdant-oublie-pari-syrien-trump:claim-9572e899e6f2de",
      "reviewedAt": "2026-06-28T07:49:26.691Z",
      "reviewedBy": "bluetouff",
      "kind": "unclassified-assertion",
      "note": "check ok"
    },
    {
      "claimId": "mou-usa-iran-juin-2026:claim-53f72b2cc65c8b",
      "reviewedAt": "2026-06-28T07:49:45.429Z",
      "reviewedBy": "bluetouff",
      "kind": "unclassified-assertion",
      "note": "check ok"
    },
    {
      "claimId": "mou-usa-iran-juin-2026:claim-5aa40dfe4d1681",
      "reviewedAt": "2026-06-28T07:50:04.657Z",
      "reviewedBy": "bluetouff",
      "kind": "unclassified-assertion",
      "note": "check ok"
    },
    {
      "claimId": "or-banques-centrales-dedollarisation-tonnes:claim-a9f51d1a7f729b",
      "reviewedAt": "2026-06-28T10:59:39.094Z",
      "reviewedBy": "bluetouff",
      "kind": "unclassified-assertion",
      "note": "Chiffres World Gold Council check ok"
    },
    {
      "claimId": "point-situation-detroit-ormuz-avril-2026:claim-65fdda88dd927a",
      "reviewedAt": "2026-06-28T08:08:50.913Z",
      "reviewedBy": "bluetouff",
      "kind": "scénario",
      "note": "check ok"
    },
    {
      "claimId": "private-credit-2026-shadow-banking:claim-ab348e06f4f898",
      "reviewedAt": "2026-06-28T08:10:33.954Z",
      "reviewedBy": "bluetouff",
      "kind": "unclassified-assertion",
      "note": "check ok"
    },
    {
      "claimId": "private-credit-semi-liquide-gating-hlend-2026:claim-8f8cb4289f94c9",
      "reviewedAt": "2026-06-28T08:05:08.228Z",
      "reviewedBy": "bluetouff",
      "kind": "unclassified-assertion",
      "note": "check ok"
    },
    {
      "claimId": "prix-import-mai-2026-petits-caracteres:claim-015a303dfb8141",
      "reviewedAt": "2026-06-28T08:04:13.234Z",
      "reviewedBy": "bluetouff",
      "kind": "unclassified-assertion",
      "note": "check ok"
    },
    {
      "claimId": "repo-collateral-fabrique-liquidite:claim-1d27489fce2f3d",
      "reviewedAt": "2026-06-28T07:32:40.709Z",
      "reviewedBy": "bluetouff",
      "kind": "unclassified-assertion",
      "note": "check ok"
    },
    {
      "claimId": "repo-collateral-fabrique-liquidite:claim-33d309c1f1c890",
      "reviewedAt": "2026-06-28T07:33:06.673Z",
      "reviewedBy": "bluetouff",
      "kind": "unclassified-assertion",
      "note": "check ok"
    },
    {
      "claimId": "repo-collateral-fabrique-liquidite:claim-6c73edffd81b5a",
      "reviewedAt": "2026-06-28T07:29:27.122Z",
      "reviewedBy": "bluetouff",
      "kind": "unclassified-assertion",
      "note": "check ok"
    },
    {
      "claimId": "repo-collateral-fabrique-liquidite:claim-7f68da4654e069",
      "reviewedAt": "2026-06-28T07:32:21.853Z",
      "reviewedBy": "bluetouff",
      "kind": "unclassified-assertion",
      "note": "check ok"
    },
    {
      "claimId": "repo-collateral-fabrique-liquidite:claim-ef43bae647c24e",
      "reviewedAt": "2026-06-28T07:32:01.414Z",
      "reviewedBy": "bluetouff",
      "kind": "unclassified-assertion",
      "note": "check ok"
    },
    {
      "claimId": "risque-inflationniste-2026:claim-58a2426ff0d266",
      "reviewedAt": "2026-06-28T08:05:26.413Z",
      "reviewedBy": "bluetouff",
      "kind": "estimation",
      "note": "check ok"
    },
    {
      "claimId": "shadow-banking-intermediation-non-bancaire:claim-4cc832f4ccaaed",
      "reviewedAt": "2026-06-28T07:28:01.528Z",
      "reviewedBy": "bluetouff",
      "kind": "unclassified-assertion",
      "note": "check ok"
    },
    {
      "claimId": "softbank-margin-loan:claim-60c57cb9495b49",
      "reviewedAt": "2026-06-28T08:06:03.200Z",
      "reviewedBy": "bluetouff",
      "kind": "unclassified-assertion",
      "note": "check ok"
    },
    {
      "claimId": "spacex-ipo-tapis-rouge-sec:claim-a3851a14f211ce",
      "reviewedAt": "2026-06-28T08:05:44.541Z",
      "reviewedBy": "bluetouff",
      "kind": "unclassified-assertion",
      "note": "check ok"
    },
    {
      "claimId": "taux-francais-pas-de-frexit:claim-a0da71d1213132",
      "reviewedAt": "2026-06-28T08:08:13.750Z",
      "reviewedBy": "bluetouff",
      "kind": "unclassified-assertion",
      "note": "check ok"
    },
    {
      "claimId": "trump-famine-arme-destruction-massive:claim-f88baa2756e24e",
      "reviewedAt": "2026-06-28T08:09:10.091Z",
      "reviewedBy": "bluetouff",
      "kind": "unclassified-assertion",
      "note": "check ok"
    },
    {
      "claimId": "warsh-premier-fomc-juin-2026:claim-09d0b410305b16",
      "reviewedAt": "2026-06-28T07:52:33.273Z",
      "reviewedBy": "bluetouff",
      "kind": "unclassified-assertion",
      "note": "check ok"
    },
    {
      "claimId": "warsh-premier-fomc-juin-2026:claim-1f779ec723ed82",
      "reviewedAt": "2026-06-28T07:52:51.135Z",
      "reviewedBy": "bluetouff",
      "kind": "unclassified-assertion",
      "note": "check ok"
    },
    {
      "claimId": "warsh-premier-fomc-juin-2026:claim-3bc5dc6fa1fcb7",
      "reviewedAt": "2026-06-28T07:51:38.478Z",
      "reviewedBy": "bluetouff",
      "kind": "unclassified-assertion",
      "note": "check ok"
    },
    {
      "claimId": "warsh-premier-fomc-juin-2026:claim-5578b2f34d0b6d",
      "reviewedAt": "2026-06-28T07:52:14.837Z",
      "reviewedBy": "bluetouff",
      "kind": "unclassified-assertion",
      "note": "check ok"
    },
    {
      "claimId": "warsh-premier-fomc-juin-2026:claim-66511c45d60eb9",
      "reviewedAt": "2026-06-28T07:51:20.978Z",
      "reviewedBy": "bluetouff",
      "kind": "scénario",
      "note": "check ok"
    },
    {
      "claimId": "warsh-premier-fomc-juin-2026:claim-b1cb566936222b",
      "reviewedAt": "2026-06-28T07:50:25.795Z",
      "reviewedBy": "bluetouff",
      "kind": "unclassified-assertion",
      "note": "check ok"
    },
    {
      "claimId": "warsh-premier-fomc-juin-2026:claim-d70c4509e9346c",
      "reviewedAt": "2026-06-28T07:50:43.628Z",
      "reviewedBy": "bluetouff",
      "kind": "unclassified-assertion",
      "note": "check ok"
    },
    {
      "claimId": "warsh-premier-fomc-juin-2026:claim-e804e7aef70318",
      "reviewedAt": "2026-06-28T07:51:01.946Z",
      "reviewedBy": "bluetouff",
      "kind": "unclassified-assertion",
      "note": "check ok"
    },
    {
      "status": "canonical",
      "claimId": "bale-iii-rollback-regulateurs-us-capital-bancaire:claim-6721d4dbc25aec",
      "reviewedAt": "2026-07-18T00:00:00.000Z",
      "reviewedBy": "codex-source-audit",
      "kind": "fait",
      "note": "Type et relation source validés sur la déclaration officielle de Michelle Bowman. Le texte décrit une proposition, pas la règle finale adoptée en novembre 2025.",
      "proofDepth": "direct-proof",
      "evidenceLocator": {
        "type": "paragraph",
        "value": "Paragraphe commençant par « For U.S. GSIBs » : remplacement du coussin fixe de 2 % par la moitié de la surcharge GSIB method 1."
      },
      "sourceUrl": "https://www.federalreserve.gov/newsevents/pressreleases/bowman-statement-20250625.htm",
      "sourceDate": "2025-06-25",
      "sourceType": "primary"
    },
    {
      "status": "canonical",
      "claimId": "ethereum-tradfi-infrastructure-finance:claim-5f1c2944670a81",
      "reviewedAt": "2026-07-18T00:00:00.000Z",
      "reviewedBy": "codex-source-audit",
      "kind": "fait",
      "note": "Type et formulation validés contre la description explicite de l'architecture traditionnelle par la BIS.",
      "proofDepth": "direct-proof",
      "evidenceLocator": {
        "type": "paragraph",
        "value": "Introduction, paragraphes 14 à 15 : bases propriétaires en silos, messageries tierces, réconciliation séparée puis règlement final."
      },
      "sourceUrl": "https://www.bis.org/publ/arpdf/ar2023e3.htm",
      "sourceDate": "2023-06-20",
      "sourceType": "primary"
    }
  ]
}
