{
  "schemaVersion": "2",
  "frameId": "20260718T002435+0200-3c51fbf89bec-29617804460-1",
  "date": "2026-07-18",
  "observedAt": "2026-07-17T22:16:07.000Z",
  "retrievedAt": "2026-07-17T22:25:23.327Z",
  "computedAt": "2026-07-18T00:24:35+02:00",
  "gitSha": "3c51fbf89bec0c6ff5f273cbd9c286b354205b3b",
  "previousFrameHash": "40443b8f11458c1e50eaa378209cce6165491eba4385c9205d0f44507f7435f3",
  "attestation": {
    "provider": "github-sigstore",
    "reference": "https://github.com/bluetouff/l0g/actions/runs/29617804460",
    "subjects": [
      "/agents.json",
      "/openapi.json",
      "/api/v1/integrity.json"
    ]
  },
  "contemporaryHashes": [
    {
      "path": "/agents.json",
      "sha256": "4194ce503197495ff171c63ed34f01c0837afc9387b9e8ea932a70855e4caf2c",
      "bytes": 6970,
      "canonicalization": "integrity-manifest-v1"
    },
    {
      "path": "/openapi.json",
      "sha256": "17356a76da582bc7797851d820325b945ed84d688bc866e4949b0e6982b9f602",
      "bytes": 85207,
      "canonicalization": "integrity-manifest-v1"
    },
    {
      "path": "/api/v1/catalog.json",
      "sha256": "f5558e5b416a642efacaa09b313e293d9bc487ffc2bebcd698614b4510436fbb",
      "bytes": 1001496,
      "canonicalization": "integrity-manifest-v1"
    },
    {
      "path": "/api/v1/search-index.json",
      "sha256": "8eb0693ceadbaf906fe819a0d4a2b6c730201396539b4cc362f2a15a18c1bb00",
      "bytes": 2990081,
      "canonicalization": "integrity-manifest-v1"
    },
    {
      "path": "/api/v1/claims.json",
      "sha256": "4b0fa935c4500404b59311d4f036146f78993d70510abb0b0e0628ae1852551b",
      "bytes": 502080,
      "canonicalization": "integrity-manifest-v1"
    },
    {
      "path": "/api/v1/evidence-graph.json",
      "sha256": "9642a23bf7c3112477a2b90e21a1d578a042cc4c2945e39c29807679ca5feaac",
      "bytes": 467953,
      "canonicalization": "integrity-manifest-v1"
    },
    {
      "path": "/api/v1/sources.json",
      "sha256": "71fb93ba7c3b6faf24615f87d87bee1a967cb69116980f16fdd3890e4b64b1f6",
      "bytes": 26836,
      "canonicalization": "integrity-manifest-v1"
    },
    {
      "path": "/api/v1/freshness.json",
      "sha256": "8d480b5696d033ff8748049071b91fadec8590dba702816a5c2217a81869c447",
      "bytes": 13754,
      "canonicalization": "integrity-manifest-v1"
    },
    {
      "path": "/api/v1/changes.json",
      "sha256": "522414c51f0305ae8f1eac17bb892e144ef26ec0ef7b4523167de62c0613a735",
      "bytes": 214614,
      "canonicalization": "integrity-manifest-v1"
    },
    {
      "path": "/api/v1/risk-diff.json",
      "sha256": "cf01b5c048263fd829303aa3223afb33d8476140dd108476ece466a0c7f57d5f",
      "bytes": 149045,
      "canonicalization": "canonical-json-v1"
    },
    {
      "path": "/api/v1/risk.json",
      "sha256": "13f3dd4fa8dc727e723ab6449802a36806a392c2244c27ca5a18b9cdc9e82b57",
      "bytes": 11250,
      "canonicalization": "canonical-json-v1"
    },
    {
      "path": "/api/v1/debt-risk.json",
      "sha256": "b83cf45beda2d89db8215d053020ce056a29f664b4ef0f6294a6607a891602f6",
      "bytes": 6433,
      "canonicalization": "canonical-json-v1"
    },
    {
      "path": "/api/v1/signals/history.json",
      "sha256": "d4e0bdcd57b08ee2cafc8c22df857d6d676ceef2c5a17ebad578a38a706f886c",
      "bytes": 295077,
      "canonicalization": "integrity-manifest-v1"
    }
  ],
  "signals": [
    {
      "recordType": "observation",
      "schemaVersion": "2",
      "recordId": "obs:debt:2026-07-17T22:24:35.000Z:6c8478349c26",
      "sourceRecordId": null,
      "instrument": "debt",
      "seriesId": "l0g.signal.debt-stress",
      "seriesSlug": "thermometre-stress-dette",
      "name": "Thermomètre de stress de la dette l0g",
      "shortName": "Stress de la dette l0g",
      "citationName": "Thermomètre de stress de la dette l0g",
      "label": "Debt Risk Radar",
      "seriesDate": "2026-07-17T22:24:35.000Z",
      "observedAt": "2026-07-17T22:16:07.000Z",
      "sourcePublishedAt": "2026-07-17T22:16:07.000Z",
      "retrievedAt": "2026-07-17T22:25:23.327Z",
      "computedAt": "2026-07-17T22:24:35.000Z",
      "archivedAt": null,
      "value": 54,
      "rawValue": 54.269720892493694,
      "scale": 100,
      "level": "Élevé",
      "tone": "elevated",
      "identityVersion": "1.0.0",
      "methodologyVersion": "1.0.0",
      "methodologyVersionStatus": "versioned",
      "methodologyEffectiveFrom": "2026-07-17",
      "sourceUrl": "https://debt.l0g.fr/latest.json",
      "methodologyUrl": "https://l0g.fr/methodologie/debt-risk-radar/",
      "methodologyChangelogUrl": "https://l0g.fr/changelog-editorial/",
      "sourceSnapshotUrl": "https://l0g.fr/api/v1/debt-risk.json",
      "calculatorRepo": "https://github.com/bluetouff/debt-risk-radar",
      "calculatorRevision": null,
      "snapshotHash": "6c8478349c26b4e08d4b2f20a87b961559eca45b8c97e5ed2f3c1580baf7e1c2",
      "archiveFrameId": null,
      "archiveFrameHash": null,
      "appendOnlyVerified": false,
      "pointInTime": true,
      "backtestUsable": true,
      "limitations": [
        "Score normalisé par instrument, pas une probabilité.",
        "seriesDate date la publication l0g ; observedAt reste nullable si la source amont ne fournit pas sa date."
      ]
    },
    {
      "recordType": "observation",
      "schemaVersion": "2",
      "recordId": "obs:energie:2026-07-17T22:24:35.000Z:8c60a31ea583",
      "sourceRecordId": null,
      "instrument": "energie",
      "seriesId": "l0g.signal.energy-market-stress",
      "seriesSlug": "indice-tension-energie",
      "name": "Indice de tension des marchés de l’énergie l0g",
      "shortName": "Tension énergie l0g",
      "citationName": "Indice de tension des marchés de l’énergie l0g",
      "label": "Energie Monitor",
      "seriesDate": "2026-07-17T22:24:35.000Z",
      "observedAt": null,
      "sourcePublishedAt": null,
      "retrievedAt": null,
      "computedAt": "2026-07-17T22:24:35.000Z",
      "archivedAt": null,
      "value": 45,
      "rawValue": 45,
      "scale": 100,
      "level": "Normal",
      "tone": "moderate",
      "identityVersion": "1.0.0",
      "methodologyVersion": "1.0.0",
      "methodologyVersionStatus": "versioned",
      "methodologyEffectiveFrom": "2026-07-17",
      "sourceUrl": "https://energie.l0g.fr",
      "methodologyUrl": "https://l0g.fr/methodologie/energie/",
      "methodologyChangelogUrl": "https://l0g.fr/changelog-editorial/",
      "sourceSnapshotUrl": "https://l0g.fr/api/v1/risk.json",
      "calculatorRepo": null,
      "calculatorRevision": null,
      "snapshotHash": "8c60a31ea583dde99f4cb52ab4d44e1c9ca82637eb1486ce49e08f0a7a1bedcf",
      "archiveFrameId": null,
      "archiveFrameHash": null,
      "appendOnlyVerified": false,
      "pointInTime": true,
      "backtestUsable": true,
      "limitations": [
        "Score normalisé par instrument, pas une probabilité.",
        "seriesDate date la publication l0g ; observedAt reste nullable si la source amont ne fournit pas sa date.",
        "Date de publication de la source amont non exposée par le snapshot historique."
      ]
    },
    {
      "recordType": "observation",
      "schemaVersion": "2",
      "recordId": "obs:eu:2026-07-17T22:24:35.000Z:5b37f213a051",
      "sourceRecordId": null,
      "instrument": "eu",
      "seriesId": "l0g.signal.euro-macro-stress",
      "seriesSlug": "barometre-stress-macro-euro",
      "name": "Baromètre de stress macro zone euro l0g",
      "shortName": "Stress macro euro l0g",
      "citationName": "Baromètre de stress macro zone euro l0g",
      "label": "EU Macro Dashboard",
      "seriesDate": "2026-07-17T22:24:35.000Z",
      "observedAt": null,
      "sourcePublishedAt": null,
      "retrievedAt": null,
      "computedAt": "2026-07-17T22:24:35.000Z",
      "archivedAt": null,
      "value": 41,
      "rawValue": 41,
      "scale": 100,
      "level": "Risk-On",
      "tone": "calm",
      "identityVersion": "1.0.0",
      "methodologyVersion": "1.0.0",
      "methodologyVersionStatus": "versioned",
      "methodologyEffectiveFrom": "2026-07-17",
      "sourceUrl": "https://euro.l0g.fr",
      "methodologyUrl": "https://l0g.fr/methodologie/euro-macro/",
      "methodologyChangelogUrl": "https://l0g.fr/changelog-editorial/",
      "sourceSnapshotUrl": "https://l0g.fr/api/v1/risk.json",
      "calculatorRepo": null,
      "calculatorRevision": null,
      "snapshotHash": "5b37f213a0514f6da34571603870067a899b2ce952c1122a257225f901a01f84",
      "archiveFrameId": null,
      "archiveFrameHash": null,
      "appendOnlyVerified": false,
      "pointInTime": true,
      "backtestUsable": true,
      "limitations": [
        "Score normalisé par instrument, pas une probabilité.",
        "seriesDate date la publication l0g ; observedAt reste nullable si la source amont ne fournit pas sa date.",
        "Date de publication de la source amont non exposée par le snapshot historique."
      ]
    },
    {
      "recordType": "observation",
      "schemaVersion": "2",
      "recordId": "obs:us:2026-07-17T22:24:35.000Z:6eeb16dc602e",
      "sourceRecordId": null,
      "instrument": "us",
      "seriesId": "l0g.signal.us-macro-stress",
      "seriesSlug": "barometre-stress-macro-us",
      "name": "Baromètre de stress macro américain l0g",
      "shortName": "Stress macro US l0g",
      "citationName": "Baromètre de stress macro américain l0g",
      "label": "US Macro Dashboard",
      "seriesDate": "2026-07-17T22:24:35.000Z",
      "observedAt": null,
      "sourcePublishedAt": null,
      "retrievedAt": null,
      "computedAt": "2026-07-17T22:24:35.000Z",
      "archivedAt": null,
      "value": 43,
      "rawValue": 43,
      "scale": 100,
      "level": "Modéré",
      "tone": "moderate",
      "identityVersion": "1.0.0",
      "methodologyVersion": "1.0.0",
      "methodologyVersionStatus": "versioned",
      "methodologyEffectiveFrom": "2026-07-17",
      "sourceUrl": "https://us.l0g.fr",
      "methodologyUrl": "https://l0g.fr/methodologie/us-macro/",
      "methodologyChangelogUrl": "https://l0g.fr/changelog-editorial/",
      "sourceSnapshotUrl": "https://l0g.fr/api/v1/risk.json",
      "calculatorRepo": null,
      "calculatorRevision": null,
      "snapshotHash": "6eeb16dc602e2db2a189315af67446c68a1da8c4bbcf087a12fb95b7c3ad5d5c",
      "archiveFrameId": null,
      "archiveFrameHash": null,
      "appendOnlyVerified": false,
      "pointInTime": true,
      "backtestUsable": true,
      "limitations": [
        "Score normalisé par instrument, pas une probabilité.",
        "seriesDate date la publication l0g ; observedAt reste nullable si la source amont ne fournit pas sa date.",
        "Date de publication de la source amont non exposée par le snapshot historique."
      ]
    },
    {
      "recordType": "observation",
      "schemaVersion": "2",
      "recordId": "obs:yen:2026-07-17T22:24:35.000Z:1ae30525f14b",
      "sourceRecordId": null,
      "instrument": "yen",
      "seriesId": "l0g.signal.yen-carry-fragility",
      "seriesSlug": "thermometre-fragilite-carry-yen",
      "name": "Thermomètre de fragilité du carry yen l0g",
      "shortName": "Fragilité carry yen l0g",
      "citationName": "Thermomètre de fragilité du carry yen l0g",
      "label": "Yen Carry Monitor",
      "seriesDate": "2026-07-17T22:24:35.000Z",
      "observedAt": null,
      "sourcePublishedAt": null,
      "retrievedAt": null,
      "computedAt": "2026-07-17T22:24:35.000Z",
      "archivedAt": null,
      "value": 45,
      "rawValue": 45,
      "scale": 100,
      "level": "Modéré",
      "tone": "moderate",
      "identityVersion": "1.0.0",
      "methodologyVersion": "1.0.0",
      "methodologyVersionStatus": "versioned",
      "methodologyEffectiveFrom": "2026-07-17",
      "sourceUrl": "https://yct.l0g.fr",
      "methodologyUrl": "https://l0g.fr/methodologie/yen-carry/",
      "methodologyChangelogUrl": "https://l0g.fr/changelog-editorial/",
      "sourceSnapshotUrl": "https://l0g.fr/api/v1/risk.json",
      "calculatorRepo": null,
      "calculatorRevision": null,
      "snapshotHash": "1ae30525f14ba69ed43266be34d567ccc99a8597e38ac932e68bba3494fb2a93",
      "archiveFrameId": null,
      "archiveFrameHash": null,
      "appendOnlyVerified": false,
      "pointInTime": true,
      "backtestUsable": true,
      "limitations": [
        "Score normalisé par instrument, pas une probabilité.",
        "seriesDate date la publication l0g ; observedAt reste nullable si la source amont ne fournit pas sa date.",
        "Date de publication de la source amont non exposée par le snapshot historique."
      ]
    }
  ],
  "freshness": {
    "generated": "2026-07-18T00:24:35+02:00",
    "signalFreshness": [
      {
        "key": "us",
        "label": "US Macro Dashboard",
        "source": "https://us.l0g.fr",
        "methodology": "https://l0g.fr/methodologie/us-macro/",
        "observedAt": "2026-07-17T22:16:07.000Z",
        "sourcePublishedAt": null,
        "retrievedAt": null,
        "computedAt": "2026-07-18T00:24:35+02:00",
        "staleAfter": "P7D",
        "expiresAt": "2026-07-24T22:16:07.000Z",
        "timelinessStatus": "fresh",
        "coverageStatus": "partial",
        "coverage": {
          "signalPresent": true,
          "observedAt": true,
          "sourcePublishedAt": false,
          "retrievedAt": false,
          "computedAt": true,
          "staleAfter": true
        },
        "missing": [
          "sourcePublishedAt",
          "retrievedAt"
        ],
        "note": "Temporalité issue du snapshot agrégé disponible. Les dates sourcePublishedAt et retrievedAt restent nulles tant que le dashboard amont ne les expose pas."
      },
      {
        "key": "eu",
        "label": "EU Macro Dashboard",
        "source": "https://euro.l0g.fr",
        "methodology": "https://l0g.fr/methodologie/euro-macro/",
        "observedAt": "2026-07-17T22:16:07.000Z",
        "sourcePublishedAt": null,
        "retrievedAt": null,
        "computedAt": "2026-07-18T00:24:35+02:00",
        "staleAfter": "P7D",
        "expiresAt": "2026-07-24T22:16:07.000Z",
        "timelinessStatus": "fresh",
        "coverageStatus": "partial",
        "coverage": {
          "signalPresent": true,
          "observedAt": true,
          "sourcePublishedAt": false,
          "retrievedAt": false,
          "computedAt": true,
          "staleAfter": true
        },
        "missing": [
          "sourcePublishedAt",
          "retrievedAt"
        ],
        "note": "Temporalité issue du snapshot agrégé disponible. Les dates sourcePublishedAt et retrievedAt restent nulles tant que le dashboard amont ne les expose pas."
      },
      {
        "key": "yen",
        "label": "Yen Carry Monitor",
        "source": "https://yct.l0g.fr",
        "methodology": "https://l0g.fr/methodologie/yen-carry/",
        "observedAt": "2026-07-17T22:16:07.000Z",
        "sourcePublishedAt": null,
        "retrievedAt": null,
        "computedAt": "2026-07-18T00:24:35+02:00",
        "staleAfter": "P7D",
        "expiresAt": "2026-07-24T22:16:07.000Z",
        "timelinessStatus": "fresh",
        "coverageStatus": "partial",
        "coverage": {
          "signalPresent": true,
          "observedAt": true,
          "sourcePublishedAt": false,
          "retrievedAt": false,
          "computedAt": true,
          "staleAfter": true
        },
        "missing": [
          "sourcePublishedAt",
          "retrievedAt"
        ],
        "note": "Temporalité issue du snapshot agrégé disponible. Les dates sourcePublishedAt et retrievedAt restent nulles tant que le dashboard amont ne les expose pas."
      },
      {
        "key": "energie",
        "label": "Energie Monitor",
        "source": "https://energie.l0g.fr",
        "methodology": "https://l0g.fr/methodologie/energie/",
        "observedAt": "2026-07-17T22:16:07.000Z",
        "sourcePublishedAt": null,
        "retrievedAt": null,
        "computedAt": "2026-07-18T00:24:35+02:00",
        "staleAfter": "P7D",
        "expiresAt": "2026-07-24T22:16:07.000Z",
        "timelinessStatus": "fresh",
        "coverageStatus": "partial",
        "coverage": {
          "signalPresent": true,
          "observedAt": true,
          "sourcePublishedAt": false,
          "retrievedAt": false,
          "computedAt": true,
          "staleAfter": true
        },
        "missing": [
          "sourcePublishedAt",
          "retrievedAt"
        ],
        "note": "Temporalité issue du snapshot agrégé disponible. Les dates sourcePublishedAt et retrievedAt restent nulles tant que le dashboard amont ne les expose pas."
      },
      {
        "key": "debt",
        "label": "Debt Risk Radar",
        "source": "https://debt.l0g.fr",
        "methodology": "https://l0g.fr/methodologie/debt-risk-radar/",
        "observedAt": "2026-07-17T22:16:07.000Z",
        "sourcePublishedAt": null,
        "retrievedAt": null,
        "computedAt": "2026-07-18T00:24:35+02:00",
        "staleAfter": "P7D",
        "expiresAt": "2026-07-24T22:16:07.000Z",
        "timelinessStatus": "fresh",
        "coverageStatus": "partial",
        "coverage": {
          "signalPresent": true,
          "observedAt": true,
          "sourcePublishedAt": false,
          "retrievedAt": false,
          "computedAt": true,
          "staleAfter": true
        },
        "missing": [
          "sourcePublishedAt",
          "retrievedAt"
        ],
        "note": "Temporalité issue du snapshot agrégé disponible. Les dates sourcePublishedAt et retrievedAt restent nulles tant que le dashboard amont ne les expose pas."
      }
    ],
    "policy": {
      "rule": "Les agents doivent privilégier date/updated pour le contenu éditorial, seriesDate pour la publication des signaux, observedAt pour la date économique amont, puis computedAt/generated pour la fraîcheur du fichier.",
      "caveat": "l0g.fr n’est pas un flux temps réel strict ; les snapshots indiquent leur date utile. Les champs sourcePublishedAt et retrievedAt restent explicites et peuvent être null quand la source amont ne les expose pas ; indexedAt décrit seulement l’indexation du lien dans l’artefact.",
      "correctionPolicy": "https://l0g.fr/protocole-editorial/",
      "changelog": "https://l0g.fr/changelog-editorial/"
    }
  },
  "changes": {
    "generated": "2026-07-18T00:24:35+02:00",
    "latest": [
      {
        "id": "d6220ae8c3d01957",
        "date": "2026-07-17T18:46:00.000Z",
        "type": "article-published",
        "contentType": "article",
        "language": "en",
        "slug": "chip-relapse-bear-market-record-profits",
        "title": "The chip relapse: a bear market on record profits",
        "url": "https://l0g.fr/en/analysis/chip-relapse-bear-market-record-profits/",
        "changedFields": [
          "title",
          "description",
          "body",
          "evidence"
        ],
        "summary": "Publication de l’analyse : The chip relapse: a bear market on record profits.",
        "objectId": "article:en:chip-relapse-bear-market-record-profits",
        "previousVersion": null,
        "currentVersion": "2026-07-17T18:46:00.000Z",
        "previousHash": null,
        "currentHash": "a855161b09b37f1589a5285d02d74ffbc6752bbed93ae38f43b21764e5d4e4e4",
        "replaces": null,
        "semanticChange": "publication",
        "correctionReason": null,
        "diffStatus": "current-only"
      },
      {
        "id": "9a54f0fe15f301c0",
        "date": "2026-07-17T18:43:00.000Z",
        "type": "article-published",
        "contentType": "article",
        "language": "fr",
        "slug": "rechute-des-puces-bear-market-profits-records",
        "title": "La rechute des puces : un bear market sur fond de profits records",
        "url": "https://l0g.fr/posts/rechute-des-puces-bear-market-profits-records/",
        "changedFields": [
          "title",
          "description",
          "body",
          "evidence"
        ],
        "summary": "Publication de l’analyse : La rechute des puces : un bear market sur fond de profits records.",
        "objectId": "article:rechute-des-puces-bear-market-profits-records",
        "previousVersion": null,
        "currentVersion": "2026-07-17T18:43:00.000Z",
        "previousHash": null,
        "currentHash": "006d528f6542b8e7226dede5a1d25c6500a9aefe4b55162bbac9c0d41d4d85b0",
        "replaces": null,
        "semanticChange": "publication",
        "correctionReason": null,
        "diffStatus": "current-only"
      },
      {
        "id": "ebbd2a88a0897980",
        "date": "2026-07-17T12:48:00.000Z",
        "type": "article-published",
        "contentType": "article",
        "language": "en",
        "slug": "truth-api-presidential-speech-market-data-feed",
        "title": "Truth API: the presidential word becomes a paid market data feed",
        "url": "https://l0g.fr/en/analysis/truth-api-presidential-speech-market-data-feed/",
        "changedFields": [
          "title",
          "description",
          "body",
          "evidence"
        ],
        "summary": "Publication de l’analyse : Truth API: the presidential word becomes a paid market data feed.",
        "objectId": "article:en:truth-api-presidential-speech-market-data-feed",
        "previousVersion": null,
        "currentVersion": "2026-07-17T12:48:00.000Z",
        "previousHash": null,
        "currentHash": "871105e7b87970b11240b6b7ca0c0eb6f46c78b8946f864c674a5a523f12186f",
        "replaces": null,
        "semanticChange": "publication",
        "correctionReason": null,
        "diffStatus": "current-only"
      },
      {
        "id": "975c6f84e3982f8d",
        "date": "2026-07-17T12:45:00.000Z",
        "type": "article-published",
        "contentType": "article",
        "language": "fr",
        "slug": "truth-api-parole-presidentielle-flux-de-marche",
        "title": "Truth API : la parole présidentielle devient un flux de marché payant",
        "url": "https://l0g.fr/posts/truth-api-parole-presidentielle-flux-de-marche/",
        "changedFields": [
          "title",
          "description",
          "body",
          "evidence"
        ],
        "summary": "Publication de l’analyse : Truth API : la parole présidentielle devient un flux de marché payant.",
        "objectId": "article:truth-api-parole-presidentielle-flux-de-marche",
        "previousVersion": null,
        "currentVersion": "2026-07-17T12:45:00.000Z",
        "previousHash": null,
        "currentHash": "0251fd9a35aa226924c90193325fa573990fc8505d2802b80d38e643410fb713",
        "replaces": null,
        "semanticChange": "publication",
        "correctionReason": null,
        "diffStatus": "current-only"
      },
      {
        "id": "076e50f91d410fd2",
        "date": "2026-07-17T09:58:00.000Z",
        "type": "article-published",
        "contentType": "article",
        "language": "en",
        "slug": "gulf-ghost-tankers-the-meter-is-running",
        "title": "Ghost tankers: in the Gulf, the meter runs at $100,000 a day",
        "url": "https://l0g.fr/en/analysis/gulf-ghost-tankers-the-meter-is-running/",
        "changedFields": [
          "title",
          "description",
          "body",
          "evidence"
        ],
        "summary": "Publication de l’analyse : Ghost tankers: in the Gulf, the meter runs at $100,000 a day.",
        "objectId": "article:en:gulf-ghost-tankers-the-meter-is-running",
        "previousVersion": null,
        "currentVersion": "2026-07-17T09:58:00.000Z",
        "previousHash": null,
        "currentHash": "1e019697ed78509a4acb3387d3adf8d22cd4e25b724ce15e8f6cc81de3fbcf67",
        "replaces": null,
        "semanticChange": "publication",
        "correctionReason": null,
        "diffStatus": "current-only"
      },
      {
        "id": "be54ffb13dd5e6f8",
        "date": "2026-07-17T09:55:00.000Z",
        "type": "article-published",
        "contentType": "article",
        "language": "fr",
        "slug": "tankers-fantomes-golfe-le-compteur-tourne",
        "title": "Tankers fantômes : dans le Golfe, le compteur tourne à 100 000 dollars par jour",
        "url": "https://l0g.fr/posts/tankers-fantomes-golfe-le-compteur-tourne/",
        "changedFields": [
          "title",
          "description",
          "body",
          "evidence"
        ],
        "summary": "Publication de l’analyse : Tankers fantômes : dans le Golfe, le compteur tourne à 100 000 dollars par jour.",
        "objectId": "article:tankers-fantomes-golfe-le-compteur-tourne",
        "previousVersion": null,
        "currentVersion": "2026-07-17T09:55:00.000Z",
        "previousHash": null,
        "currentHash": "921881f58bec65f2107a842ad91bf29f67aa2044f88f9e2075c13e725994e228",
        "replaces": null,
        "semanticChange": "publication",
        "correctionReason": null,
        "diffStatus": "current-only"
      },
      {
        "id": "e051690096c48a51",
        "date": "2026-07-17T07:40:00.000Z",
        "type": "article-published",
        "contentType": "article",
        "language": "en",
        "slug": "strategic-petroleum-reserves-buffer-round-two",
        "title": "Strategic reserves: the state of the buffer before round two",
        "url": "https://l0g.fr/en/analysis/strategic-petroleum-reserves-buffer-round-two/",
        "changedFields": [
          "title",
          "description",
          "body",
          "evidence"
        ],
        "summary": "Publication de l’analyse : Strategic reserves: the state of the buffer before round two.",
        "objectId": "article:en:strategic-petroleum-reserves-buffer-round-two",
        "previousVersion": null,
        "currentVersion": "2026-07-17T07:40:00.000Z",
        "previousHash": null,
        "currentHash": "75f37d9e168ddfe33447dd41011baf179a3c1e7ab3911a0543dd0c5d4071f2be",
        "replaces": null,
        "semanticChange": "publication",
        "correctionReason": null,
        "diffStatus": "current-only"
      },
      {
        "id": "2d900a0310c1972b",
        "date": "2026-07-17T07:30:00.000Z",
        "type": "article-published",
        "contentType": "article",
        "language": "fr",
        "slug": "reserves-strategiques-petrole-matelas-deuxieme-round",
        "title": "Réserves stratégiques : l'état du matelas avant le deuxième round",
        "url": "https://l0g.fr/posts/reserves-strategiques-petrole-matelas-deuxieme-round/",
        "changedFields": [
          "title",
          "description",
          "body",
          "evidence"
        ],
        "summary": "Publication de l’analyse : Réserves stratégiques : l'état du matelas avant le deuxième round.",
        "objectId": "article:reserves-strategiques-petrole-matelas-deuxieme-round",
        "previousVersion": null,
        "currentVersion": "2026-07-17T07:30:00.000Z",
        "previousHash": null,
        "currentHash": "07ba72b6f528305e89af4598e00208348ab2ddecd5b73cf4327e78674b1ad49b",
        "replaces": null,
        "semanticChange": "publication",
        "correctionReason": null,
        "diffStatus": "current-only"
      },
      {
        "id": "02fac577399a7a43",
        "date": "2026-07-17T00:00:00.000Z",
        "type": "editorial-change",
        "contentType": "policy",
        "language": "fr",
        "slug": "2026-07-17-données",
        "title": "Registre des séries de risque nommées et versionnées",
        "url": "https://l0g.fr/changelog-editorial/",
        "changedFields": [
          "protocol",
          "methodology",
          "source-policy"
        ],
        "summary": "Chaque jauge du tableau consolidé reçoit un identifiant stable, un nom citable, des exports JSON, NDJSON et CSV dédiés, une date de série issue de la frame Black Box et une version méthodologique. Les frames antérieures au registre restent explicitement non versionnées ; aucun backfill rétroactif n’est produit.",
        "objectId": "policy:2026-07-17-données",
        "previousVersion": null,
        "currentVersion": "2026-07-17T00:00:00.000Z",
        "previousHash": null,
        "currentHash": "dd00da9f60137b0f762972f8ea761056b0f59b680f74ba4bf4ded8197668294b",
        "replaces": null,
        "semanticChange": "editorial-policy-change",
        "correctionReason": null,
        "diffStatus": "current-only"
      },
      {
        "id": "5faafa5906e8cbff",
        "date": "2026-07-17T00:00:00.000Z",
        "type": "editorial-change",
        "contentType": "policy",
        "language": "fr",
        "slug": "2026-07-17-méthode",
        "title": "Claims structurants typés et sélectionnés par le risque",
        "url": "https://l0g.fr/changelog-editorial/",
        "changedFields": [
          "protocol",
          "methodology",
          "source-policy"
        ],
        "summary": "La surface limite désormais chaque article à trois claims structurants maximum et supprime le type assertion non classée. Chaque claim est classée en fait, estimation, inférence ou scénario ; ce typage heuristique reste distinct d’une revue canonique complète.",
        "objectId": "policy:2026-07-17-méthode",
        "previousVersion": null,
        "currentVersion": "2026-07-17T00:00:00.000Z",
        "previousHash": null,
        "currentHash": "e2d57e3bcf8e770acaa59831eade935fb003f6eac6d7abad428647706684873b",
        "replaces": null,
        "semanticChange": "editorial-policy-change",
        "correctionReason": null,
        "diffStatus": "current-only"
      },
      {
        "id": "f21162c2ffad50f4",
        "date": "2026-07-16T19:40:00.000Z",
        "type": "article-published",
        "contentType": "article",
        "language": "en",
        "slug": "nav-loans-the-hidden-fund-level-leverage",
        "title": "NAV loans: the leverage no one sees",
        "url": "https://l0g.fr/en/analysis/nav-loans-the-hidden-fund-level-leverage/",
        "changedFields": [
          "title",
          "description",
          "body",
          "evidence"
        ],
        "summary": "Publication de l’analyse : NAV loans: the leverage no one sees.",
        "objectId": "article:en:nav-loans-the-hidden-fund-level-leverage",
        "previousVersion": null,
        "currentVersion": "2026-07-16T19:40:00.000Z",
        "previousHash": null,
        "currentHash": "989c93a9d120213295860eac7ad774568f08d9d502e6fc6d0a5d5c3e03dda500",
        "replaces": null,
        "semanticChange": "publication",
        "correctionReason": null,
        "diffStatus": "current-only"
      },
      {
        "id": "c8b352a316196dd5",
        "date": "2026-07-16T19:30:00.000Z",
        "type": "article-published",
        "contentType": "article",
        "language": "fr",
        "slug": "nav-loan-levier-cache-fonds-credit-prive",
        "title": "NAV loan : le levier que personne ne voit",
        "url": "https://l0g.fr/posts/nav-loan-levier-cache-fonds-credit-prive/",
        "changedFields": [
          "title",
          "description",
          "body",
          "evidence"
        ],
        "summary": "Publication de l’analyse : NAV loan : le levier que personne ne voit.",
        "objectId": "article:nav-loan-levier-cache-fonds-credit-prive",
        "previousVersion": null,
        "currentVersion": "2026-07-16T19:30:00.000Z",
        "previousHash": null,
        "currentHash": "46741feab5213a2ddfd4ccbca1d8695aadea65c8aa76f74e40889c1b0f2aec46",
        "replaces": null,
        "semanticChange": "publication",
        "correctionReason": null,
        "diffStatus": "current-only"
      },
      {
        "id": "7a27dadc34b67e42",
        "date": "2026-07-16T16:40:00.000Z",
        "type": "guide-published",
        "contentType": "guide",
        "language": "fr",
        "slug": "lire-une-notation-de-credit",
        "title": "Lire une notation de crédit : échelles, défaut et le conflit du modèle émetteur-payeur",
        "url": "https://l0g.fr/guides/lire-une-notation-de-credit/",
        "changedFields": [
          "title",
          "description",
          "body"
        ],
        "summary": "Publication du guide : Lire une notation de crédit : échelles, défaut et le conflit du modèle émetteur-payeur.",
        "objectId": "guide:lire-une-notation-de-credit",
        "previousVersion": null,
        "currentVersion": "2026-07-16T16:40:00.000Z",
        "previousHash": null,
        "currentHash": "6abc933be737a1aef57651001b51cd65a7b818bbc663b2d27e38284acc7e3b10",
        "replaces": null,
        "semanticChange": "publication",
        "correctionReason": null,
        "diffStatus": "current-only"
      },
      {
        "id": "b65836329367fc71",
        "date": "2026-07-16T16:40:00.000Z",
        "type": "guide-published",
        "contentType": "guide",
        "language": "en",
        "slug": "read-credit-ratings",
        "title": "Reading a credit rating: scales, default and the issuer-pays conflict",
        "url": "https://l0g.fr/en/guides/read-credit-ratings/",
        "changedFields": [
          "title",
          "description",
          "body"
        ],
        "summary": "Publication du guide : Reading a credit rating: scales, default and the issuer-pays conflict.",
        "objectId": "guide:en:read-credit-ratings",
        "previousVersion": null,
        "currentVersion": "2026-07-16T16:40:00.000Z",
        "previousHash": null,
        "currentHash": "a4823481ec5613bcca871fac17bd817f2d1cac47b134a3f1470a627a32f67659",
        "replaces": null,
        "semanticChange": "publication",
        "correctionReason": null,
        "diffStatus": "current-only"
      },
      {
        "id": "6de870adbd383b67",
        "date": "2026-07-16T16:20:00.000Z",
        "type": "guide-published",
        "contentType": "guide",
        "language": "fr",
        "slug": "lire-le-marche-du-gaz-et-du-gnl",
        "title": "Lire le marché du gaz et du GNL : les trois indices et l'arbitrage entre bassins",
        "url": "https://l0g.fr/guides/lire-le-marche-du-gaz-et-du-gnl/",
        "changedFields": [
          "title",
          "description",
          "body"
        ],
        "summary": "Publication du guide : Lire le marché du gaz et du GNL : les trois indices et l'arbitrage entre bassins.",
        "objectId": "guide:lire-le-marche-du-gaz-et-du-gnl",
        "previousVersion": null,
        "currentVersion": "2026-07-16T16:20:00.000Z",
        "previousHash": null,
        "currentHash": "74385985f04e22ae5c332af49c265113c261f94ea6f0bdd3185151d5fb476172",
        "replaces": null,
        "semanticChange": "publication",
        "correctionReason": null,
        "diffStatus": "current-only"
      },
      {
        "id": "a9c733a51f3f3395",
        "date": "2026-07-16T16:20:00.000Z",
        "type": "guide-published",
        "contentType": "guide",
        "language": "en",
        "slug": "read-gas-lng-market",
        "title": "Reading the gas and LNG market: the three benchmarks and inter-basin arbitrage",
        "url": "https://l0g.fr/en/guides/read-gas-lng-market/",
        "changedFields": [
          "title",
          "description",
          "body"
        ],
        "summary": "Publication du guide : Reading the gas and LNG market: the three benchmarks and inter-basin arbitrage.",
        "objectId": "guide:en:read-gas-lng-market",
        "previousVersion": null,
        "currentVersion": "2026-07-16T16:20:00.000Z",
        "previousHash": null,
        "currentHash": "b9fc49e01c777ac86b22bddcce42a4a1af828df71750aec494e9a8dc4d9f3b16",
        "replaces": null,
        "semanticChange": "publication",
        "correctionReason": null,
        "diffStatus": "current-only"
      },
      {
        "id": "34d272366ffc3157",
        "date": "2026-07-16T16:00:00.000Z",
        "type": "guide-published",
        "contentType": "guide",
        "language": "en",
        "slug": "read-life-insurer-health",
        "title": "Reading a life insurer's soundness: capital, reinsurance and opaque assets",
        "url": "https://l0g.fr/en/guides/read-life-insurer-health/",
        "changedFields": [
          "title",
          "description",
          "body"
        ],
        "summary": "Publication du guide : Reading a life insurer's soundness: capital, reinsurance and opaque assets.",
        "objectId": "guide:en:read-life-insurer-health",
        "previousVersion": null,
        "currentVersion": "2026-07-16T16:00:00.000Z",
        "previousHash": null,
        "currentHash": "7a1698739ae26beff08f90b13b35a2f5de6b8f8fa0c08f7beeb8ab8cce7c7c0a",
        "replaces": null,
        "semanticChange": "publication",
        "correctionReason": null,
        "diffStatus": "current-only"
      },
      {
        "id": "c701bb06312de8dd",
        "date": "2026-07-16T16:00:00.000Z",
        "type": "guide-published",
        "contentType": "guide",
        "language": "fr",
        "slug": "lire-la-solidite-d-un-assureur-vie",
        "title": "Lire la solidité d'un assureur-vie : capital, réassurance et actifs opaques",
        "url": "https://l0g.fr/guides/lire-la-solidite-d-un-assureur-vie/",
        "changedFields": [
          "title",
          "description",
          "body"
        ],
        "summary": "Publication du guide : Lire la solidité d'un assureur-vie : capital, réassurance et actifs opaques.",
        "objectId": "guide:lire-la-solidite-d-un-assureur-vie",
        "previousVersion": null,
        "currentVersion": "2026-07-16T16:00:00.000Z",
        "previousHash": null,
        "currentHash": "68ee96f9751c5748116049e921e00ba8b2fd737d37cfa68e7e950bbe5d8f12ca",
        "replaces": null,
        "semanticChange": "publication",
        "correctionReason": null,
        "diffStatus": "current-only"
      },
      {
        "id": "53b611cf84556d1a",
        "date": "2026-07-16T12:40:00.000Z",
        "type": "article-published",
        "contentType": "article",
        "language": "en",
        "slug": "the-august-clocks-us-iran-memorandum-deadlines",
        "title": "The broken clocks of the US-Iran memorandum",
        "url": "https://l0g.fr/en/analysis/the-august-clocks-us-iran-memorandum-deadlines/",
        "changedFields": [
          "title",
          "description",
          "body",
          "evidence"
        ],
        "summary": "Publication de l’analyse : The broken clocks of the US-Iran memorandum.",
        "objectId": "article:en:the-august-clocks-us-iran-memorandum-deadlines",
        "previousVersion": null,
        "currentVersion": "2026-07-16T12:40:00.000Z",
        "previousHash": null,
        "currentHash": "9e20affc2da01c194925610c4576cea3d07f00bc1bca467386ca0e493b9cc77d",
        "replaces": null,
        "semanticChange": "publication",
        "correctionReason": null,
        "diffStatus": "current-only"
      },
      {
        "id": "580583e322caa4e3",
        "date": "2026-07-16T12:30:00.000Z",
        "type": "article-published",
        "contentType": "article",
        "language": "fr",
        "slug": "les-horloges-d-aout-mou-usa-iran-echeances",
        "title": "Les horloges brisées du mémorandum USA-Iran",
        "url": "https://l0g.fr/posts/les-horloges-d-aout-mou-usa-iran-echeances/",
        "changedFields": [
          "title",
          "description",
          "body",
          "evidence"
        ],
        "summary": "Publication de l’analyse : Les horloges brisées du mémorandum USA-Iran.",
        "objectId": "article:les-horloges-d-aout-mou-usa-iran-echeances",
        "previousVersion": null,
        "currentVersion": "2026-07-16T12:30:00.000Z",
        "previousHash": null,
        "currentHash": "bd52616a3f9a7c26c1fd20f310e14156023711aee80d018ee32ffd6934e96745",
        "replaces": null,
        "semanticChange": "publication",
        "correctionReason": null,
        "diffStatus": "current-only"
      }
    ]
  },
  "limitations": [
    "La frame prouve les octets et métadonnées archivés, pas la vérité économique des modèles.",
    "Les claims restent canoniques en français ; les traductions pointent vers ces preuves sans duplication."
  ],
  "frameHash": "d57ba2437fa5d678fe5220ce5eee5fc48630921106617f9655cb0076b017369f"
}
